polymerge/__init__.py
polymerge/__main__.py
polymerge/cfg.py
polymerge/polymerge.py
polymerge/polytracker.py
zbyte_polyfile/__init__.py
zbyte_polyfile/__main__.py
zbyte_polyfile/arithmetic.py
zbyte_polyfile/ast.py
zbyte_polyfile/debugger.py
zbyte_polyfile/expressions.py
zbyte_polyfile/fileutils.py
zbyte_polyfile/html.py
zbyte_polyfile/iterators.py
zbyte_polyfile/jpeg.py
zbyte_polyfile/kaitaimatcher.py
zbyte_polyfile/languagematcher.py
zbyte_polyfile/logger.py
zbyte_polyfile/magic.py
zbyte_polyfile/nes.py
zbyte_polyfile/nitf.py
zbyte_polyfile/pdf.py
zbyte_polyfile/pickles.py
zbyte_polyfile/polyfile.py
zbyte_polyfile/profiling.py
zbyte_polyfile/repl.py
zbyte_polyfile/search.py
zbyte_polyfile/serialization.py
zbyte_polyfile/structmatcher.py
zbyte_polyfile/structs.py
zbyte_polyfile/wildcards.py
zbyte_polyfile/zipmatcher.py
zbyte_polyfile/http/__init__.py
zbyte_polyfile/http/defacto.py
zbyte_polyfile/http/deprecated.py
zbyte_polyfile/http/experimental.py
zbyte_polyfile/http/http_11.py
zbyte_polyfile/http/matcher.py
zbyte_polyfile/http/structured_headers.py
zbyte_polyfile/kaitai/__init__.py
zbyte_polyfile/kaitai/compiler.py
zbyte_polyfile/kaitai/parser.py
zbyte_polyfile/kaitai/parsers/__init__.py
zbyte_polyfile/kaitai/parsers/aix_utmp.py
zbyte_polyfile/kaitai/parsers/allegro_dat.py
zbyte_polyfile/kaitai/parsers/andes_firmware.py
zbyte_polyfile/kaitai/parsers/android_bootldr_asus.py
zbyte_polyfile/kaitai/parsers/android_bootldr_huawei.py
zbyte_polyfile/kaitai/parsers/android_bootldr_qcom.py
zbyte_polyfile/kaitai/parsers/android_dto.py
zbyte_polyfile/kaitai/parsers/android_img.py
zbyte_polyfile/kaitai/parsers/android_nanoapp_header.py
zbyte_polyfile/kaitai/parsers/android_opengl_shaders_cache.py
zbyte_polyfile/kaitai/parsers/android_sparse.py
zbyte_polyfile/kaitai/parsers/android_super.py
zbyte_polyfile/kaitai/parsers/apm_partition_table.py
zbyte_polyfile/kaitai/parsers/apple_single_double.py
zbyte_polyfile/kaitai/parsers/asn1_der.py
zbyte_polyfile/kaitai/parsers/au.py
zbyte_polyfile-20250310.0.dist-info/LICENSE
zbyte_polyfile-20250310.0.dist-info/METADATA
zbyte_polyfile-20250310.0.dist-info/WHEEL
zbyte_polyfile-20250310.0.dist-info/entry_points.txt
zbyte_polyfile-20250310.0.dist-info/top_level.txt
zbyte_polyfile-20250310.0.dist-info/RECORD
